LICENSE
MANIFEST.in
README.md
setup.py
./version.py
pygraphdb/__init__.py
pygraphdb/connections.py
pygraphdb/cursors.py
pygraphdb/graphdb_free_config.py
pygraphdb/management.py
pygraphdb.egg-info/PKG-INFO
pygraphdb.egg-info/SOURCES.txt
pygraphdb.egg-info/dependency_links.txt
pygraphdb.egg-info/requires.txt
pygraphdb.egg-info/top_level.txt