Metadata-Version: 2.1
Name: pygraphdb
Version: 2.0.3
Summary: A connect graphdb package
Home-page: https://gitee.com/maxbanana/graphdb
Author: hongbo liu
Author-email: bananabo@foxmail.com
License: Apache
Classifier: Programming Language :: Python :: 3
Classifier: License :: OSI Approved :: Apache Software License
Classifier: Operating System :: OS Independent
Requires-Python: >=3.6
License-File: LICENSE
Requires-Dist: requests
